sac2021/__init__.py
sac2021/const.py
sac2021/data.py
sac2021/finetune.py
sac2021/loss.py
sac2021/pretrain.py
sac2021/sac2021.py
sac2021/scheduler.py
sac2021/train.py
sac2021-0.0.3.dist-info/METADATA
sac2021-0.0.3.dist-info/WHEEL
sac2021-0.0.3.dist-info/top_level.txt
sac2021-0.0.3.dist-info/RECORD
