Metadata-Version: 2.1
Name: sac2021
Version: 0.0.3
Summary: 5th solution for Samsung AI Challenge for Scientific Discovery (2021)
Home-page: https://github.com/dohlee/samsung-ai-challenge-solution
Author: Dohoon Lee
Author-email: dohlee.bioinfo@gmail.com
License: MIT
Keywords: artificial intelligence,cheminformatics,molecular property prediction,quantum chemistry
Classifier: Development Status :: 4 - Beta
Classifier: Intended Audience :: Developers
Classifier: Topic :: Scientific/Engineering :: Artificial Intelligence
Classifier: License :: OSI Approved :: MIT License
Classifier: Programming Language :: Python :: 3.9
Requires-Dist: einops (>=0.3)
Requires-Dist: rdkit
Requires-Dist: numpy
Requires-Dist: torch (>=1.6)
